pauli/__init__.py
pauli-0.0.1.dist-info/LICENSE
pauli-0.0.1.dist-info/METADATA
pauli-0.0.1.dist-info/WHEEL
pauli-0.0.1.dist-info/top_level.txt
pauli-0.0.1.dist-info/RECORD
