Metadata-Version: 2.1
Name: pauli
Version: 0.0.1
Summary: Utility for managing Azure Pipelines components in bulk
Home-page: https://github.com/swellaby/pauli
Author: Swellaby
Author-email: opensource@example.com
License: MIT
Platform: UNKNOWN
